docs/conf.py
tests/conftest.py
tests/test_bos.py
tests/test_computetools.py
tests/test_core.py
tests/test_diagnostics.py
tests/test_pif.py
tests/fixtures/block_on_spring/block_on_spring.py
tests/fixtures/particle_in_field/particle_in_field.py
turbopy/__init__.py
turbopy/__version__.py
turbopy/computetools.py
turbopy/constructors.py
turbopy/core.py
turbopy/diagnostics.py
turbopy-2023.6.9.dist-info/LICENSE
turbopy-2023.6.9.dist-info/METADATA
turbopy-2023.6.9.dist-info/WHEEL
turbopy-2023.6.9.dist-info/top_level.txt
turbopy-2023.6.9.dist-info/RECORD
