Metadata-Version: 2.1
Name: turbopy
Version: 2023.6.9
Summary: A lightweight computational physics framework, which implements a "Simulation, PhysicsModule, ComputeTool" class hierarchy.
Home-page: https://github.com/NRL-Plasma-Physics-Division/turbopy
Author: Nancy Isner
Author-email: ndisner10@gmail.com
Classifier: License :: CC0 1.0 Universal (CC0 1.0) Public Domain Dedication
Classifier: Programming Language :: Python
Classifier: Programming Language :: Python :: 3
Classifier: Programming Language :: Python :: 3.9
Classifier: Programming Language :: Python :: Implementation :: CPython
Classifier: Programming Language :: Python :: Implementation :: PyPy
Requires-Python: >=3.9.0
License-File: LICENSE
Requires-Dist: numpy
Requires-Dist: scipy
Requires-Dist: qtoml
Requires-Dist: xarray
